backup_airtable/__init__.py
backup_airtable/cli.py
backup_airtable-0.2.0.dist-info/entry_points.txt
backup_airtable-0.2.0.dist-info/licenses/LICENSE
backup_airtable-0.2.0.dist-info/WHEEL
backup_airtable-0.2.0.dist-info/METADATA
backup_airtable-0.2.0.dist-info/RECORD
