Metadata-Version: 2.4
Name: backup-airtable
Version: 0.2.0
Summary: Quickly and painlessly dump all your Airtable schemas & data to JSON.
Keywords: airtable,backup,exporter
Author-email: David Brownman <beamneocube@gmail.com>
Requires-Python: >=3.10
Classifier: Programming Language :: Python :: 3
Classifier: Development Status :: 4 - Beta
Classifier: Environment :: Console
Classifier: License :: OSI Approved :: Apache Software License
Classifier: Operating System :: OS Independent
Classifier: Topic :: System :: Archiving :: Backup
License-File: LICENSE
Requires-Dist: click==8.1.3
Requires-Dist: httpx==0.27.0
Requires-Dist: pyright==1.1.394 ; extra == "ci"
Requires-Dist: ruff==0.9.7 ; extra == "ci"
Requires-Dist: twine==6.0.1 ; extra == "release"
Requires-Dist: build==1.2.2 ; extra == "release"
Requires-Dist: pytest==7.3.1 ; extra == "test"
Requires-Dist: pytest-httpx==0.30.0 ; extra == "test"
Requires-Dist: pytest-freezer==0.4.8 ; extra == "test"
Project-URL: Author, https://xavd.id
Project-URL: Bug Tracker, https://github.com/xavdid/backup-airtable/issues
Project-URL: Changelog, https://github.com/xavdid/backup-airtable/blob/main/CHANGELOG.md
Project-URL: Homepage, https://github.com/xavdid/backup-airtable
Provides-Extra: ci
Provides-Extra: release
Provides-Extra: test
